strapi_kit/__init__.py
strapi_kit/__version__.py
strapi_kit/_version.py
strapi_kit/config_provider.py
strapi_kit/protocols.py
strapi_kit/auth/__init__.py
strapi_kit/auth/api_token.py
strapi_kit/cache/__init__.py
strapi_kit/cache/schema_cache.py
strapi_kit/client/__init__.py
strapi_kit/client/async_client.py
strapi_kit/client/base.py
strapi_kit/client/sync_client.py
strapi_kit/exceptions/__init__.py
strapi_kit/exceptions/errors.py
strapi_kit/export/__init__.py
strapi_kit/export/exporter.py
strapi_kit/export/importer.py
strapi_kit/export/media_handler.py
strapi_kit/export/relation_resolver.py
strapi_kit/models/__init__.py
strapi_kit/models/bulk.py
strapi_kit/models/config.py
strapi_kit/models/enums.py
strapi_kit/models/export_format.py
strapi_kit/models/import_options.py
strapi_kit/models/schema.py
strapi_kit/models/request/__init__.py
strapi_kit/models/request/fields.py
strapi_kit/models/request/filters.py
strapi_kit/models/request/pagination.py
strapi_kit/models/request/populate.py
strapi_kit/models/request/query.py
strapi_kit/models/request/sort.py
strapi_kit/models/response/__init__.py
strapi_kit/models/response/base.py
strapi_kit/models/response/component.py
strapi_kit/models/response/media.py
strapi_kit/models/response/meta.py
strapi_kit/models/response/normalized.py
strapi_kit/models/response/relation.py
strapi_kit/models/response/v4.py
strapi_kit/models/response/v5.py
strapi_kit/operations/__init__.py
strapi_kit/operations/media.py
strapi_kit/operations/streaming.py
strapi_kit/parsers/__init__.py
strapi_kit/parsers/version_detecting.py
strapi_kit/utils/__init__.py
strapi_kit/utils/rate_limiter.py
strapi_kit/utils/uid.py
strapi_kit-0.0.2.dist-info/METADATA
strapi_kit-0.0.2.dist-info/WHEEL
strapi_kit-0.0.2.dist-info/licenses/LICENSE
strapi_kit-0.0.2.dist-info/RECORD
