Metadata-Version: 2.4
Name: strapi-kit
Version: 0.0.2
Summary: A modern Python client for Strapi CMS with import/export capabilities
Project-URL: Homepage, https://github.com/mehdizare/strapi-kit
Project-URL: Documentation, https://mehdizare.github.io/strapi-kit/
Project-URL: Repository, https://github.com/mehdizare/strapi-kit
Project-URL: Issues, https://github.com/mehdizare/strapi-kit/issues
Author: Mehdi Zare
License: MIT
License-File: LICENSE
Keywords: api,client,cms,export,import,strapi
Classifier: Development Status :: 4 - Beta
Classifier: Intended Audience :: Developers
Classifier: License :: OSI Approved :: MIT License
Classifier: Programming Language :: Python :: 3
Classifier: Programming Language :: Python :: 3.12
Classifier: Programming Language :: Python :: 3.13
Classifier: Programming Language :: Python :: 3.14
Classifier: Topic :: Software Development :: Libraries :: Python Modules
Requires-Python: >=3.12
Requires-Dist: httpx>=0.28.1
Requires-Dist: orjson>=3.11.0
Requires-Dist: pydantic-settings<3.0,>=2.7.0
Requires-Dist: pydantic<3.0,>=2.10.0
Requires-Dist: python-dateutil>=2.9.0
Requires-Dist: tenacity>=9.0.0
Requires-Dist: typing-extensions>=4.15.0
Provides-Extra: dev
Requires-Dist: bandit[toml]>=1.9.3; extra == 'dev'
Requires-Dist: detect-secrets>=1.5.0; extra == 'dev'
Requires-Dist: mypy>=1.19.1; extra == 'dev'
Requires-Dist: pre-commit>=4.5.0; extra == 'dev'
Requires-Dist: pytest-asyncio>=0.24.0; extra == 'dev'
Requires-Dist: pytest-cov>=6.0.0; extra == 'dev'
Requires-Dist: pytest-mock>=3.15.0; extra == 'dev'
Requires-Dist: pytest>=8.3.0; extra == 'dev'
Requires-Dist: respx>=0.22.0; extra == 'dev'
Requires-Dist: ruff>=0.14.14; extra == 'dev'
Requires-Dist: safety<4.0.0,>=2.3.0; extra == 'dev'
Provides-Extra: docs
Requires-Dist: mkdocs-material>=9.7.0; extra == 'docs'
Requires-Dist: mkdocs>=1.6.1; extra == 'docs'
Requires-Dist: mkdocstrings[python]>=1.0.0; extra == 'docs'
